agent_task/__init__.py
agent_task/api.py
agent_task/cli.py
agent_task/paths.py
agent_task/show_dirs.py
agent_task/task_manager.py
agent_task-0.1.3.dist-info/METADATA
agent_task-0.1.3.dist-info/WHEEL
agent_task-0.1.3.dist-info/entry_points.txt
agent_task-0.1.3.dist-info/RECORD
