Metadata-Version: 2.4
Name: agent-task
Version: 0.1.3
Summary: Task-Specific AI Agent Platform for Cursor AI
Project-URL: Homepage, https://taskhub.microwiseai.dev
Project-URL: Repository, https://github.com/microwiseai/agent-task
Project-URL: Documentation, https://taskhub.microwiseai.dev/docs
Author-email: MicroWise AI <contact@microwiseai.dev>
License-Expression: MIT
Keywords: agent,ai,cli,cursor
Classifier: Development Status :: 3 - Alpha
Classifier: Intended Audience :: Developers
Classifier: License :: OSI Approved :: MIT License
Classifier: Programming Language :: Python :: 3
Classifier: Programming Language :: Python :: 3.8
Classifier: Programming Language :: Python :: 3.9
Classifier: Programming Language :: Python :: 3.10
Classifier: Programming Language :: Python :: 3.11
Classifier: Topic :: Software Development :: Libraries :: Python Modules
Requires-Python: >=3.8
Requires-Dist: appdirs>=1.4.0
Requires-Dist: cleo>=2.0.0
Requires-Dist: pyyaml>=6.0
Requires-Dist: requests>=2.28.0
Requires-Dist: rich>=13.0.0
Provides-Extra: dev
Requires-Dist: black>=23.0.0; extra == 'dev'
Requires-Dist: isort>=5.0.0; extra == 'dev'
Requires-Dist: mypy>=1.0.0; extra == 'dev'
Requires-Dist: pytest>=7.0.0; extra == 'dev'
Requires-Dist: ruff>=0.1.0; extra == 'dev'
